x7/__init__.py
x7/view/__init__.py
x7/view/__main__.py
x7/view/__version__.py
x7/view/details.py
x7/view/dialogs.py
x7/view/digi.py
x7/view/digibase.py
x7/view/digiview.py
x7/view/errors.py
x7/view/event.py
x7/view/icons.py
x7/view/needs_test.py
x7/view/notes.py
x7/view/pc_bug.py
x7/view/platform.py
x7/view/shell_tools.py
x7/view/style.py
x7/view/style_show.py
x7/view/undo.py
x7/view/widgets.py
x7/view/modes/__init__.py
x7/view/modes/add.py
x7/view/modes/adddrag.py
x7/view/modes/addmulti.py
x7/view/modes/common.py
x7/view/modes/select.py
x7/view/modes/zoom.py
x7/view/resources/__init__.py
x7/view/resources/icons/__init__.py
x7/view/resources/icons/pencil-10-16x16.png
x7/view/resources/icons/pencil-10-24x24.png
x7/view/resources/icons/pencil-10-32x32.png
x7/view/resources/icons/pencil-10-64x64.png
x7/view/resources/icons/pencil-16x16.png
x7/view/resources/icons/pencil-24x24.png
x7/view/resources/icons/pencil-32x32.png
x7/view/resources/icons/pencil-64x64.png
x7/view/resources/icons/redo-16x16.png
x7/view/resources/icons/redo-24x24.png
x7/view/resources/icons/redo-32x32.png
x7/view/resources/icons/redo-64x64.png
x7/view/resources/icons/undo-16x16.png
x7/view/resources/icons/undo-24x24.png
x7/view/resources/icons/undo-32x32.png
x7/view/resources/icons/undo-64x64.png
x7/view/shapes/__init__.py
x7/view/shapes/curve_cmd.py
x7/view/shapes/digicurve.py
x7/view/shapes/ellipse.py
x7/view/shapes/group.py
x7/view/shapes/rect.py
x7/view/shapes/rrect.py
x7/view/shapes/shape.py
x7/view/shapes/shape_su.py
x7/view/shapes/with_holes.py
x7/view/tests/__init__.py
x7/view/tests/canvas.py
x7/view/tests/cursors.py
x7/view/tests/events.py
x7/view/tests/menu.py
x7/view/tests/menu_post.py
x7/view/tests/round_frame.py
x7/view/tests/save_as.py
x7/view/tests/styles.py
x7/view/tests/transform.py
x7_view-0.5.0.dist-info/LICENSE
x7_view-0.5.0.dist-info/METADATA
x7_view-0.5.0.dist-info/WHEEL
x7_view-0.5.0.dist-info/entry_points.txt
x7_view-0.5.0.dist-info/top_level.txt
x7_view-0.5.0.dist-info/RECORD
